{
    "posts": [
        {
            "createtime": "2015-12-17T00:55:19+08:00", 
            "image": "http://upload-images.jianshu.io/upload_images/49368-a3f8c805a0a2721d.png?imageMogr2/auto-orient/strip%7CimageView2/1/w/300/h/300", 
            "link": "http://www.jianshu.com/p/218f4bc2239d", 
            "title": "UICollectionView"
        }, 
        {
            "createtime": "2015-12-03T20:52:47+08:00", 
            "image": null, 
            "link": "http://www.jianshu.com/p/46ab25a84e9c", 
            "title": "算法初探"
        }, 
        {
            "createtime": "2015-11-27T23:27:05+08:00", 
            "image": null, 
            "link": "http://www.jianshu.com/p/1949c8ea1e1a", 
            "title": "小结"
        }, 
        {
            "createtime": "2015-11-27T00:59:10+08:00", 
            "image": "http://upload-images.jianshu.io/upload_images/49368-3721dc751c7a1b88.png?imageMogr2/auto-orient/strip%7CimageView2/1/w/300/h/300", 
            "link": "http://www.jianshu.com/p/ef18a2ae9600", 
            "title": "Unit Testing Tutorial:Mocking Objects(Part2)"
        }, 
        {
            "createtime": "2015-11-23T22:47:11+08:00", 
            "image": "http://upload-images.jianshu.io/upload_images/49368-3b1e35abe52bcd54.png?imageMogr2/auto-orient/strip%7CimageView2/1/w/300/h/300", 
            "link": "http://www.jianshu.com/p/17553a452619", 
            "title": "Unit Testing Tutorial:Mocking Objects(Part1)"
        }, 
        {
            "createtime": "2015-11-20T23:15:01+08:00", 
            "image": null, 
            "link": "http://www.jianshu.com/p/c1b972e808db", 
            "title": "一些iOS开发教程网站"
        }, 
        {
            "createtime": "2015-11-19T00:23:00+08:00", 
            "image": null, 
            "link": "http://www.jianshu.com/p/8c6e096a66ce", 
            "title": "Swift 2.0中的错误处理"
        }, 
        {
            "createtime": "2015-11-18T00:13:17+08:00", 
            "image": null, 
            "link": "http://www.jianshu.com/p/57c9ce74178f", 
            "title": "Swift基础(Part1)"
        }, 
        {
            "createtime": "2015-11-15T21:01:56+08:00", 
            "image": null, 
            "link": "http://www.jianshu.com/p/20c5fd5c5dd4", 
            "title": "小结"
        }
    ], 
    "updated_at": "2016-06-22T22:27:41.786380"
}